aws_session_credentials/__init__.py
aws_session_credentials/__main__.py
aws_session_credentials/aws_session_credentials.py
aws_session_credentials-0.1.5.dist-info/METADATA
aws_session_credentials-0.1.5.dist-info/RECORD
aws_session_credentials-0.1.5.dist-info/WHEEL
aws_session_credentials-0.1.5.dist-info/entry_points.txt
aws_session_credentials-0.1.5.dist-info/top_level.txt
