Metadata-Version: 2.1
Name: aws-session-credentials
Version: 0.1.5
Summary: Manage AWS session credentials
Home-page: https://github.com/thumbtack/aws-session-credentials
Author: Thumbtack SRE
License: Apache License 2.0
Keywords: aws
Platform: UNKNOWN
Classifier: Development Status :: 5 - Production/Stable
Classifier: Environment :: Console
Classifier: Intended Audience :: Developers
Classifier: License :: OSI Approved :: Apache Software License
Classifier: Topic :: Utilities
Requires-Python: >=2.6,!=3.0.*,!=3.1.*,!=3.2.*,<4
Requires-Dist: boto3 (>=1.4.0)
Requires-Dist: botocore (>=1.5.0)
